bulk_import.py
bulkimporttools-0.0.4.dist-info/LICENSE
bulkimporttools-0.0.4.dist-info/METADATA
bulkimporttools-0.0.4.dist-info/WHEEL
bulkimporttools-0.0.4.dist-info/top_level.txt
bulkimporttools-0.0.4.dist-info/RECORD
