Metadata-Version: 2.1
Name: bulkimporttools
Version: 0.0.4
Summary: A collection of tools for importing classes and modules in bulk
Home-page: https://github.com/Mikael-MStinson/Bulk-Import
Author: Mikael Morrell-Stinson
License: UNKNOWN
Platform: UNKNOWN
Classifier: Programming Language :: Python :: 3
Classifier: Programming Language :: Python :: 3.6
Classifier: Programming Language :: Python :: 3.7
Classifier: License :: OSI Approved :: GNU General Public License v2 or later (GPLv2+)
Classifier: Operating System :: OS Independent
Classifier: Intended Audience :: Developers
Classifier: Development Status :: 1 - Planning
